.DS_Store
.gitignore
AUTHORS
HACKING
HISTORY.rst
LICENSE
MANIFEST.in
NOTICE
README.rst
setup.py
test_clint.py
tox.ini
clint/__init__.py
clint/arguments.py
clint/eng.py
clint/pipes.py
clint/resources.py
clint/utils.py
clint.egg-info/PKG-INFO
clint.egg-info/SOURCES.txt
clint.egg-info/dependency_links.txt
clint.egg-info/pbr.json
clint.egg-info/requires.txt
clint.egg-info/top_level.txt
clint/packages/__init__.py
clint/packages/appdirs.py
clint/packages/ordereddict.py
clint/packages/colorama/__init__.py
clint/packages/colorama/ansi.py
clint/packages/colorama/ansitowin32.py
clint/packages/colorama/initialise.py
clint/packages/colorama/win32.py
clint/packages/colorama/winterm.py
clint/textui/__init__.py
clint/textui/colored.py
clint/textui/cols.py
clint/textui/core.py
clint/textui/formatters.py
clint/textui/progress.py
clint/textui/prompt.py
clint/textui/validators.py